code_iq/__init__.py
code_iq/__main__.py
code_iq/commands/__init__.py
code_iq/commands/ai.py
code_iq/commands/chat.py
code_iq/commands/complete.py
code_iq/commands/document.py
code_iq/commands/enhance.py
code_iq/commands/review.py
code_iq/commands/scan.py
code_iq/commands/test.py
code_iq/main.py
code_iq-1.0.1.dist-info/LICENSE
code_iq-1.0.1.dist-info/METADATA
code_iq-1.0.1.dist-info/WHEEL
code_iq-1.0.1.dist-info/entry_points.txt
code_iq-1.0.1.dist-info/RECORD
